HBVigor/HBVigor.py
HBVigor/__init__.py
utils/__init__.py
HBVigor-0.1.4.dist-info/LICENSE
HBVigor-0.1.4.dist-info/METADATA
HBVigor-0.1.4.dist-info/WHEEL
HBVigor-0.1.4.dist-info/top_level.txt
HBVigor-0.1.4.dist-info/zip-safe
HBVigor-0.1.4.dist-info/RECORD
