Metadata-Version: 2.1
Name: HBVigor
Version: 0.1.4
Summary: HBV.
Home-page: UNKNOWN
Author: fengzhizi
Author-email: fengzhizi32@live.com
License: Mulan PSL v2
Platform: UNKNOWN
Classifier: Environment :: Web Environment
Classifier: Intended Audience :: Developers
Classifier: License :: OSI Approved :: MIT License
Classifier: Operating System :: MacOS
Classifier: Operating System :: Microsoft
Classifier: Operating System :: POSIX
Classifier: Operating System :: Unix
Classifier: Topic :: Software Development :: Libraries :: Python Modules
Classifier: Programming Language :: Python :: 3.5
Classifier: Programming Language :: Python :: 3.6
Classifier: Programming Language :: Python :: 3.7
Classifier: Programming Language :: Python :: 3.8
Classifier: Programming Language :: Python :: 3.9
Requires-Dist: scipy
Requires-Dist: numpy
Requires-Dist: astropy
